vma_nlu/__init__.py
vma_nlu/build_name_dict.py
vma_nlu/tester.py
vma_nlu/data/dictionary_normalize_date.json
vma_nlu/data/stopwords.pkl
vma_nlu/ic/__init__.py
vma_nlu/ic/logistic_regression_classifier.py
vma_nlu/ic/naive_bayes_classifier.py
vma_nlu/ic/test.py
vma_nlu/ic/weight/LR_model.pkl
vma_nlu/ic/weight/SGD_model.pkl
vma_nlu/ic/weight/naive_bayes_model.pkl
vma_nlu/ner/__init__.py
vma_nlu/ner/biaffine_extractor.py
vma_nlu/ner/date_matcher.py
vma_nlu/ner/extractor.py
vma_nlu/ner/flair_extractor.py
vma_nlu/ner/pattern_extractor.py
vma_nlu/ner/pername_matcher.py
vma_nlu/ner/time_matcher.py
vma_nlu/ner/pername_deeplearning/__init__.py
vma_nlu/ner/pername_deeplearning/config.py
vma_nlu/ner/pername_deeplearning/inference.py
vma_nlu/ner/pername_deeplearning/utils.py
vma_nlu/ner/pername_deeplearning/model/__init__.py
vma_nlu/ner/pername_deeplearning/model/model.py
vma_nlu/ner/pername_deeplearning/model/layer/FeedForward.py
vma_nlu/ner/pername_deeplearning/model/layer/__init__.py
vma_nlu/ner/pername_deeplearning/model/layer/biaffine.py
vma_nlu/ner/pername_deeplearning/model/layer/charcnn.py
vma_nlu/ner/pername_deeplearning/model/layer/featureEmbed.py
vma_nlu/ner/pername_deeplearning/model/layer/wordnet.py
vma_nlu/utils/__init__.py
vma_nlu/utils/date_pattern.py
vma_nlu/utils/pername_pattern.py
vma_nlu/utils/preproces.py
vma_nlu/utils/time_pattern.py
vma_nlu/utils/util.py
vma_nlu-1.3.9.dist-info/METADATA
vma_nlu-1.3.9.dist-info/WHEEL
vma_nlu-1.3.9.dist-info/top_level.txt
vma_nlu-1.3.9.dist-info/RECORD
