Metadata-Version: 2.1
Name: vma-nlu
Version: 1.3.9
Summary: VMA-NLU is a library to implement NLU component in virtual medical assistant.
Home-page: https://github.com/demdecuong/NER_Extractor/tree/main
Author: minhnp
Author-email: v.minhng@vinbrain.net
License: UNKNOWN
Keywords: vma_nlu
Platform: UNKNOWN
Classifier: Programming Language :: Python :: 3
Requires-Python: >=3.6
Requires-Dist: vietnam-number (==1.0.3)
Requires-Dist: pandas (==1.2.4)
Requires-Dist: numpy (==1.18.5)
Requires-Dist: torch (==1.5.1)
Requires-Dist: transformers (==4.8.2)
Requires-Dist: fasttext (==0.9.2)
Requires-Dist: sklearn
Requires-Dist: gdown
